l0/__init__.py
l0/calibration.py
l0/distributions.py
l0/gates.py
l0/layers.py
l0/penalties.py
l0/sparse.py
l0_python-0.5.0.dist-info/licenses/LICENSE
l0_python-0.5.0.dist-info/METADATA
l0_python-0.5.0.dist-info/WHEEL
l0_python-0.5.0.dist-info/top_level.txt
l0_python-0.5.0.dist-info/RECORD
