Metadata-Version: 2.4
Name: l0-python
Version: 0.5.0
Summary: L0 regularization for sparse neural networks and intelligent sampling
Author-email: PolicyEngine <hello@policyengine.org>
License: MIT License
Project-URL: Homepage, https://github.com/PolicyEngine/L0
Project-URL: Repository, https://github.com/PolicyEngine/L0
Project-URL: Documentation, https://github.com/PolicyEngine/L0#readme
Project-URL: Issues, https://github.com/PolicyEngine/L0/issues
Keywords: l0,regularization,sparsity,neural networks,calibration
Classifier: Development Status :: 4 - Beta
Classifier: Intended Audience :: Science/Research
Classifier: License :: OSI Approved :: MIT License
Classifier: Programming Language :: Python :: 3
Classifier: Programming Language :: Python :: 3.13
Classifier: Topic :: Scientific/Engineering :: Artificial Intelligence
Requires-Python: >=3.11
License-File: LICENSE
Requires-Dist: torch>=2.0.0
Requires-Dist: numpy>=1.20.0
Requires-Dist: scipy>=1.7.0
Provides-Extra: dev
Requires-Dist: pytest>=7.0; extra == "dev"
Requires-Dist: pytest-cov>=3.0; extra == "dev"
Requires-Dist: black>=22.0; extra == "dev"
Requires-Dist: build>=1.3; extra == "dev"
Requires-Dist: scikit-learn>=1.0; extra == "dev"
Requires-Dist: yaml-changelog>=0.3.0; extra == "dev"
Requires-Dist: twine>=4.0.0; extra == "dev"
Provides-Extra: docs
Requires-Dist: jupyter-book>=1.0; extra == "docs"
Requires-Dist: jupyter>=1.0; extra == "docs"
Requires-Dist: notebook>=7.0; extra == "docs"
Requires-Dist: ipykernel>=6.0; extra == "docs"
Provides-Extra: examples
Requires-Dist: matplotlib>=3.3; extra == "examples"
Requires-Dist: tqdm>=4.60; extra == "examples"
Requires-Dist: pandas>=1.3; extra == "examples"
Requires-Dist: scikit-learn>=1.0; extra == "examples"
Requires-Dist: torchvision>=0.15; extra == "examples"
Dynamic: license-file
